recall_kit/__init__.py
recall_kit/core.py
recall_kit-0.1.0.dist-info/METADATA
recall_kit-0.1.0.dist-info/WHEEL
recall_kit-0.1.0.dist-info/licenses/LICENSE
recall_kit-0.1.0.dist-info/RECORD
