Metadata-Version: 2.4
Name: recall-kit
Version: 0.1.0
Summary: Lightweight memory integration for LLMs
Project-URL: Homepage, https://github.com/username/recall-kit
Project-URL: Bug Tracker, https://github.com/username/recall-kit/issues
Author-email: recall-kit contributors <example@example.com>
License: MIT
License-File: LICENSE
Classifier: License :: OSI Approved :: MIT License
Classifier: Operating System :: OS Independent
Classifier: Programming Language :: Python :: 3
Requires-Python: >=3.7
Provides-Extra: dev
Requires-Dist: black>=23.0.0; extra == 'dev'
Requires-Dist: isort>=5.0.0; extra == 'dev'
Requires-Dist: pytest-cov>=4.0.0; extra == 'dev'
Requires-Dist: pytest>=7.0.0; extra == 'dev'
